ksef/__init__.py
ksef/cli.py
ksef/client.py
ksef/exceptions.py
ksef/models.py
ksef/stub_server.py
ksef/xsd/__init__.py
ksef_py-0.0.1a1.dist-info/METADATA
ksef_py-0.0.1a1.dist-info/WHEEL
ksef_py-0.0.1a1.dist-info/entry_points.txt
ksef_py-0.0.1a1.dist-info/RECORD
