Metadata-Version: 2.1
Name: ksef-py
Version: 0.0.1a1
Summary: Modern Python SDK + CLI for Poland's National e-Invoice System (KSeF)
Home-page: https://github.com/Kamil-Dab/ksef-py
License: MIT
Keywords: ksef,einvoice,poland,tax,api,sdk
Author: Kamil
Requires-Python: >=3.9,<4.0
Classifier: Development Status :: 3 - Alpha
Classifier: Intended Audience :: Developers
Classifier: License :: OSI Approved :: MIT License
Classifier: Programming Language :: Python :: 3
Classifier: Programming Language :: Python :: 3.9
Classifier: Programming Language :: Python :: 3.10
Classifier: Programming Language :: Python :: 3.11
Classifier: Programming Language :: Python :: 3.12
Classifier: Topic :: Office/Business :: Financial :: Accounting
Classifier: Topic :: Software Development :: Libraries :: Python Modules
Requires-Dist: click (>=8.1.0,<9.0.0)
Requires-Dist: cryptography (>=41.0.0,<42.0.0)
Requires-Dist: httpx[http2] (>=0.27.0,<0.28.0)
Requires-Dist: lxml (>=5.0.0,<6.0.0)
Requires-Dist: pydantic (>=2.0.0,<3.0.0)
Requires-Dist: pydantic-settings (>=2.0.0,<3.0.0)
Requires-Dist: python-dateutil (>=2.8.0,<3.0.0)
Requires-Dist: rich (>=13.0.0,<14.0.0)
Requires-Dist: tenacity (>=8.0.0,<9.0.0)
Requires-Dist: zeep (>=4.2.0,<5.0.0)
Project-URL: Documentation, https://ksef-py.readthedocs.io
Project-URL: Repository, https://github.com/Kamil-Dab/ksef-py
